Metadata-Version: 1.0
Name: audiblerangepy
Version: 0.0.4
Summary: `audiblerangepy` is a package for checking some frequency is audible or not for some human-being and animals
Home-page: https://github.com/k-mawa/audiblerangepy
Author: Kosuke Mawatari
Author-email: UNKNOWN
License: MIT
Keywords: audible,audible range
Platform: UNKNOWN
